syndb_cassandra/__init__.py
syndb_cassandra/constant.py
syndb_cassandra/models/__init__.py
syndb_cassandra/models/cell_structure.py
syndb_cassandra/models/organelle.py
syndb_cassandra/utils/__init__.py
syndb_cassandra/utils/column_types_to_python.py
syndb_cassandra/utils/create_materialized_view.py
syndb_cassandra/utils/misc.py
syndb_cassandra/workflow/__init__.py
syndb_cassandra/workflow/datastax.py
syndb_cassandra/workflow/rs.py
syndb_cassandra-5.2.2.dist-info/METADATA
syndb_cassandra-5.2.2.dist-info/WHEEL
syndb_cassandra-5.2.2.dist-info/RECORD
